nefertem_core/__init__.py
nefertem_core/client/__init__.py
nefertem_core/client/builder.py
nefertem_core/client/client.py
nefertem_core/metadata/__init__.py
nefertem_core/metadata/blob.py
nefertem_core/metadata/env.py
nefertem_core/metadata/report.py
nefertem_core/plugins/__init__.py
nefertem_core/plugins/builder.py
nefertem_core/plugins/factory.py
nefertem_core/plugins/plugin.py
nefertem_core/plugins/utils.py
nefertem_core/readers/__init__.py
nefertem_core/readers/builder.py
nefertem_core/readers/registry.py
nefertem_core/readers/objects/__init__.py
nefertem_core/readers/objects/_base.py
nefertem_core/readers/objects/file.py
nefertem_core/readers/objects/native.py
nefertem_core/resources/__init__.py
nefertem_core/resources/data_resource.py
nefertem_core/run/__init__.py
nefertem_core/run/builder.py
nefertem_core/run/config.py
nefertem_core/run/handler.py
nefertem_core/run/run.py
nefertem_core/run/run_info.py
nefertem_core/run/status.py
nefertem_core/stores/__init__.py
nefertem_core/stores/builder.py
nefertem_core/stores/kinds.py
nefertem_core/stores/input/__init__.py
nefertem_core/stores/input/registry.py
nefertem_core/stores/input/objects/__init__.py
nefertem_core/stores/input/objects/_base.py
nefertem_core/stores/input/objects/dummy.py
nefertem_core/stores/input/objects/local.py
nefertem_core/stores/input/objects/remote.py
nefertem_core/stores/input/objects/s3.py
nefertem_core/stores/input/objects/sql.py
nefertem_core/stores/output/__init__.py
nefertem_core/stores/output/registry.py
nefertem_core/stores/output/objects/__init__.py
nefertem_core/stores/output/objects/_base.py
nefertem_core/stores/output/objects/dummy.py
nefertem_core/stores/output/objects/local.py
nefertem_core/utils/__init__.py
nefertem_core/utils/commons.py
nefertem_core/utils/exceptions.py
nefertem_core/utils/io_utils.py
nefertem_core/utils/logger.py
nefertem_core/utils/utils.py
nefertem_core-2.0.6.dist-info/LICENSE.txt
nefertem_core-2.0.6.dist-info/METADATA
nefertem_core-2.0.6.dist-info/WHEEL
nefertem_core-2.0.6.dist-info/top_level.txt
nefertem_core-2.0.6.dist-info/RECORD
