Metadata-Version: 2.1
Name: nefertem-core
Version: 2.0.6
Summary: Python data validation library
Author-email: Fondazione Bruno Kessler <dslab@fbk.eu>, Matteo Martini <mmartini@fbk.eu>
License: Apache License
Project-URL: Homepage, https://github.com/scc-digitalhub/nefertem
Keywords: data,validation,quality
Classifier: License :: OSI Approved :: Apache Software License
Classifier: Programming Language :: Python :: 3.9
Classifier: Programming Language :: Python :: 3.10
Classifier: Programming Language :: Python :: 3.11
Requires-Python: >=3.9
License-File: LICENSE.txt
Requires-Dist: boto3
Requires-Dist: pydantic >=1.10.8,~=1.10
Requires-Dist: pandas <2.2,>=1.2
Requires-Dist: sqlalchemy ~=1.4
Requires-Dist: psutil >=5.9
Requires-Dist: requests ~=2.31
Requires-Dist: adbc-driver-manager ==0.7.0
Requires-Dist: polars
Provides-Extra: dev
Requires-Dist: black ; extra == 'dev'
Requires-Dist: pytest ; extra == 'dev'
Requires-Dist: moto ; extra == 'dev'
Requires-Dist: bumpver ; extra == 'dev'
Provides-Extra: docs
Requires-Dist: Sphinx ==5.3.0 ; extra == 'docs'
Requires-Dist: pydata-sphinx-theme ==0.13.3 ; extra == 'docs'
Requires-Dist: autodoc-pydantic ==1.8.0 ; extra == 'docs'
Requires-Dist: numpydoc ==1.5.0 ; extra == 'docs'
